odoo10_addon_account_group-10.0.1.1.0-py2.7-nspkg.pth
odoo/addons/account_group/README.rst
odoo/addons/account_group/__init__.py
odoo/addons/account_group/__manifest__.py
odoo/addons/account_group/i18n/account_group.pot
odoo/addons/account_group/i18n/es.po
odoo/addons/account_group/i18n/pt.po
odoo/addons/account_group/migrations/10.0.1.1.0/post-migration.py
odoo/addons/account_group/models/__init__.py
odoo/addons/account_group/models/account_account.py
odoo/addons/account_group/models/account_account_template.py
odoo/addons/account_group/models/account_chart_template.py
odoo/addons/account_group/models/account_group.py
odoo/addons/account_group/readme/CONFIGURE.rst
odoo/addons/account_group/readme/CONTRIBUTORS.rst
odoo/addons/account_group/readme/DESCRIPTION.rst
odoo/addons/account_group/readme/INSTALL.rst
odoo/addons/account_group/readme/ROADMAP.rst
odoo/addons/account_group/readme/USAGE.rst
odoo/addons/account_group/security/ir.model.access.csv
odoo/addons/account_group/static/description/icon.png
odoo/addons/account_group/static/description/index.html
odoo/addons/account_group/views/account_account_views.xml
odoo/addons/account_group/views/account_group_views.xml
odoo10_addon_account_group-10.0.1.1.0.dist-info/METADATA
odoo10_addon_account_group-10.0.1.1.0.dist-info/RECORD
odoo10_addon_account_group-10.0.1.1.0.dist-info/WHEEL
odoo10_addon_account_group-10.0.1.1.0.dist-info/namespace_packages.txt
odoo10_addon_account_group-10.0.1.1.0.dist-info/top_level.txt
