Metadata-Version: 2.1
Name: odoo10-addon-account-group
Version: 10.0.1.1.0
Summary: Use v11 account groups feature
Home-page: https://github.com/OCA/account-financial-tools
Author: Tecnativa,Odoo Community Association (OCA)
Author-email: support@odoo-community.org
License: AGPL-3
Platform: UNKNOWN
Classifier: Programming Language :: Python
Classifier: Framework :: Odoo
Classifier: License :: OSI Approved :: GNU Affero General Public License v3
Requires-Python: ~=2.7
Requires-Dist: odoo (<10.1dev,>=10.0)
